[
     {
          "id": 1,
          "name": "TATLILAR",
          "backgroundImg": "https://bufibu.com/qr/assets/system/images/2532676_quality3.webp",
          "urunler": [
               {
                    "id": 1,
                    "category": "Tatlılar",
                    "name":"Meyveli Gusto",
                    "img":"https://bufibu.com/qr/assets/system/images/bufibucom7589629_quality5.webp",
                    "price": 170,
                    "description": "Magnolya kreması ve gusto bisküvisi çilek muz sütlü belçika çikolatası ve krep kırtığı"
               },
               {
                    "id": 2,
                    "category": "Tatlılar",
                    "name":"Dondurmalı Profiterol",
                    "img":"https://bufibu.com/qr/assets/system/images/bufibucom7589629_quality5.webp",
                    "price": 170,
                    "description": "2 top profiterol içi krema yerine vanilyalı dondurma dolgulu ve sütlü belçika çikolatalı"
               },
               {
                    "id": 3,
                    "category": "Tatlılar",
                    "name":"Çilekli Tart",
                    "img":"https://bufibu.com/qr/assets/system/images/bufibucom882302_quality5.webp",
                    "price": 145,
                    "description": "Tart kurabiyesi, no.11 kreması çilek ve belçika çikolatası"
               },
               {
                    "id": 4,
                    "category": "Tatlılar",
                    "name":"Firuze",
                    "img":"https://bufibu.com/qr/assets/system/images/6287873_quality5.webp",
                    "price": 150,
                    "description": "Antep fıstıklı kek, karamel sos ve belçika çikolatalı mousse"
               }
          ]
         
     },
     {
          "id": 2,
          "name": "SOĞUK KAHVELER",
          "backgroundImg": "https://bufibu.com/qr/assets/system/images/bufibucom3097388_quality3.webp",
          "urunler": [
               {
                    "id": 1,
                    "category": "Soğuk Kahveler",
                    "name": "Ice Filtre Kahve",
                    "img": "https://bufibu.com/qr/assets/system/images/bufibucom2978092_quality5.webp",
                    "price": 90,
                    "description": "Özel demlenmiş natural filtre kahve ve bol miktarda buz"
               },
               {
                    "id": 2,
                    "category": "Soğuk Kahveler",
                    "name": "Ice Americano",
                    "img": "https://bufibu.com/qr/assets/system/images/6544698_quality5.webp",
                    "price": 95,
                    "description": "İsteğe göre single veya double espresso, su ve bol miktarda buz"
               },
               {
                    "id": 3,
                    "category": "Soğuk Kahveler",
                    "name": "Ice Latte",
                    "img": "https://bufibu.com/qr/assets/system/images/bufibucom9261669_quality5.webp",
                    "price": 100,
                    "description": "İsteğe göre single veya double espresso, süt ve bol miktarda buz"
               },
               {
                    "id": 4,
                    "category": "Soğuk Kahveler",
                    "name": "Affogato",
                    "img": "https://bufibu.com/qr/assets/system/images/8631020_quality5.webp",
                    "price": 95,
                    "description": "İteğe göre single veya double espresso üzerine isteğe göre 1 top dondurma"
               }
          ]
     },
     {
          "id": 3,
          "name": "BUBBLE KOKTEYLLER",
          "backgroundImg": "https://bufibu.com/qr/assets/system/images/491555_quality3.webp",
          "urunler": [
          {
               "id": 1,
               "category": "Bubble Kokteyller",
               "name": "Galaxy",
               "img": "https://bufibu.com/qr/assets/system/images/1125367_quality5.webp",
               "price": 100,
               "description":"Yaban mersin aromalı"
          },
          {
               "id": 2,
               "category": "Bubble Kokteyller",
               "name": "Bubble Tea Hibiscus",
               "img": "https://bufibu.com/qr/assets/system/images/1265971_quality5.webp",
               "price": 100,
               "description":"Hibiscus aromalı"
          },
          {
               "id": 3,
               "category": "Bubble Kokteyller",
               "name": "Maria",
               "img": "https://bufibu.com/qr/assets/system/images/7809477_quality5.webp",
               "price": 100,
               "description":"Orman meyve aromalı"
          },
          {
               "id": 4,
               "category": "Bubble Kokteyller",
               "name": "Zombie",
               "img": "https://bufibu.com/qr/assets/system/images/7991904_quality5.webp",
               "price": 100,
               "description":"Yeşil elma aromalı"
          }
     ]
     },
     {
          "id": 4,
          "name": "SICAK İÇECEKLER",
          "backgroundImg": "https://bufibu.com/qr/assets/system/images/884_quality3.webp",
          "urunler": [
          {
               "id": 1,
               "category": "Sıcak İçeekler",
               "name": "Bardak Çay",
               "img": "https://bufibu.com/qr/assets/system/images/bufibucom7086577_quality5.webp",
               "price": 25,
               "description":"Meşhur rize çayıyla demlenen siyah demlik çay"
          },
          {
               "id": 2,
               "category": "Sıcak İçeekler",
               "name": "Kupa Çay",
               "img": "https://bufibu.com/qr/assets/system/images/5271_quality5.webp",
               "price": 45,
               "description":"Meşhur rize çayıyla demlenen siyah demlik çay"
          },
          {
               "id": 3,
               "category": "Sıcak İçeekler",
               "name": "Türk Kahvesi",
               "img": "https://bufibu.com/qr/assets/system/images/qrbufibu2825_quality5.webp",
               "price": 60,
               "description":"Eşsiz lezzetiyle "
          },
          {
               "id": 4,
               "category": "Sıcak İçeekler",
               "name": "Dibek Kahvesi",
               "img": "https://bufibu.com/qr/assets/system/images/8674947_quality5.webp",
               "price": 65,
               "description":"Kendine has tadı ve aromasıyla"
          },
          {
               "id": 5,
               "category": "Sıcak İçeekler",
               "name": "Menengiç Kahvesi",
               "img": "https://bufibu.com/qr/assets/system/images/3428825_quality5.webp",
               "price": 65,
               "description":"Menengiç çekirdeklerinin vurucu lezzeti ile"
          },
          {
               "id": 6,
               "category": "Sıcak İçeekler",
               "name": "Damla Sakızlı Türk Kahvesi",
               "img": "https://bufibu.com/qr/assets/system/images/5017_quality5.webp",
               "price": 65,
               "description":"Damla sakızı severlere özel"
          },
          {
               "id": 7,
               "category": "Sıcak İçeekler",
               "name": "Sahlep",
               "img": "https://bufibu.com/qr/assets/system/images/bufibucom2538_quality5.webp",
               "price": 75,
               "description":"Gerçek süt ile tam kıvamında"
          },
          {
               "id": 8,
               "category": "Sıcak İçeekler",
               "name": "Sıcak Çikolata",
               "img": "https://bufibu.com/qr/assets/system/images/7641_quality5.webp",
               "price": 80,
               "description":"Belçika çikolatası ile orjinal kıvam"
          }
     ]
     }
    
]